omnirec_runner/__init__.py
omnirec_runner/elliot_logger_config.yml
omnirec_runner/elliot_runner.py
omnirec_runner/lenskit_runner.py
omnirec_runner/py.typed
omnirec_runner/recbole_runner.py
omnirec_runner/recpack_runner.py
omnirec_runner/runner.py
omnirec_runner/test.py
omnirec_runner-0.1.1.dist-info/METADATA
omnirec_runner-0.1.1.dist-info/WHEEL
omnirec_runner-0.1.1.dist-info/RECORD
